hyphi_gym/__init__.py
hyphi_gym/assets/Reach.xml
hyphi_gym/assets/env.blend
hyphi_gym/assets/grid.xml
hyphi_gym/assets/hyphi.png
hyphi_gym/assets/point.xml
hyphi_gym/assets/Agent/Body.obj
hyphi_gym/assets/Agent/Ears.obj
hyphi_gym/assets/Agent/Eyes.obj
hyphi_gym/assets/Agent/Hat.obj
hyphi_gym/assets/Agent/Lamp.obj
hyphi_gym/assets/Agent/Mouth.obj
hyphi_gym/assets/Agent/White.obj
hyphi_gym/assets/fetch/robot.xml
hyphi_gym/assets/fetch/shared.xml
hyphi_gym/assets/fetch/mesh/base_link_collision.stl
hyphi_gym/assets/fetch/mesh/bellows_link_collision.stl
hyphi_gym/assets/fetch/mesh/elbow_flex_link_collision.stl
hyphi_gym/assets/fetch/mesh/estop_link.stl
hyphi_gym/assets/fetch/mesh/forearm_roll_link_collision.stl
hyphi_gym/assets/fetch/mesh/gripper_link.stl
hyphi_gym/assets/fetch/mesh/head_pan_link_collision.stl
hyphi_gym/assets/fetch/mesh/head_tilt_link_collision.stl
hyphi_gym/assets/fetch/mesh/l_wheel_link_collision.stl
hyphi_gym/assets/fetch/mesh/laser_link.stl
hyphi_gym/assets/fetch/mesh/r_wheel_link_collision.stl
hyphi_gym/assets/fetch/mesh/shoulder_lift_link_collision.stl
hyphi_gym/assets/fetch/mesh/shoulder_pan_link_collision.stl
hyphi_gym/assets/fetch/mesh/torso_fixed_link.stl
hyphi_gym/assets/fetch/mesh/torso_lift_link_collision.stl
hyphi_gym/assets/fetch/mesh/upperarm_roll_link_collision.stl
hyphi_gym/assets/fetch/mesh/wrist_flex_link_collision.stl
hyphi_gym/assets/fetch/mesh/wrist_roll_link_collision.stl
hyphi_gym/assets/fetch/textures/block.png
hyphi_gym/assets/fetch/textures/block_hidden.png
hyphi_gym/common/__init__.py
hyphi_gym/common/base.py
hyphi_gym/common/board.py
hyphi_gym/common/grid.py
hyphi_gym/common/holes.py
hyphi_gym/common/maze.py
hyphi_gym/common/point.py
hyphi_gym/common/rendering.py
hyphi_gym/common/robot.py
hyphi_gym/common/simulation.py
hyphi_gym/envs/__init__.py
hyphi_gym/envs/Fetch/__init__.py
hyphi_gym/envs/FlatGrid/__init__.py
hyphi_gym/envs/GridMaze/__init__.py
hyphi_gym/envs/HoleyGrid/__init__.py
hyphi_gym/envs/HoleyPlane/__init__.py
hyphi_gym-0.8.dist-info/LICENSE
hyphi_gym-0.8.dist-info/METADATA
hyphi_gym-0.8.dist-info/WHEEL
hyphi_gym-0.8.dist-info/entry_points.txt
hyphi_gym-0.8.dist-info/top_level.txt
hyphi_gym-0.8.dist-info/RECORD
