Metadata-Version: 2.1
Name: hyphi_gym
Version: 0.8
Summary: Gymnasium benchmark suite for evaluating robustness and multi-task performance of reinforcement learning algorithms in various discrete and continuous environments.
Home-page: https://github.com/philippaltmann/hyphi-gym
Author-email: philipp@hyphi.co
License: MIT
Keywords: reinforcement-learning robustness benchmark gymnasium gridworld maze mujoco openai gym
Requires-Python: >=3.8
License-File: LICENSE
Requires-Dist: gymnasium >=0.29
Requires-Dist: numpy >=1.20
Requires-Dist: Pillow >=9.5
Requires-Dist: moviepy >=1.0
Requires-Dist: bpy ==3.6.0
Requires-Dist: mujoco ==2.3.3
Provides-Extra: all
Requires-Dist: bpy ==3.6.0 ; extra == 'all'
Requires-Dist: mujoco ==2.3.3 ; extra == 'all'
Requires-Dist: matplotlib >=3.5 ; extra == 'all'
Provides-Extra: docs
Requires-Dist: sphinx ; extra == 'docs'
Requires-Dist: furo ; extra == 'docs'
Requires-Dist: sphinx-autoapi ; extra == 'docs'
Requires-Dist: myst-parser ; extra == 'docs'
Provides-Extra: plotting
Requires-Dist: matplotlib >=3.5 ; extra == 'plotting'
Provides-Extra: rendering
Requires-Dist: bpy ==3.6.0 ; extra == 'rendering'
Provides-Extra: simulation
Requires-Dist: mujoco ==2.3.3 ; extra == 'simulation'
Provides-Extra: tests
Requires-Dist: pytest ; extra == 'tests'
Requires-Dist: black ; extra == 'tests'
